PyoSolveWrapper/SolveWrapper.py
PyoSolveWrapper/__init__.py
PyoSolveWrapper-0.3.2.dist-info/LICENSE
PyoSolveWrapper-0.3.2.dist-info/METADATA
PyoSolveWrapper-0.3.2.dist-info/WHEEL
PyoSolveWrapper-0.3.2.dist-info/top_level.txt
PyoSolveWrapper-0.3.2.dist-info/RECORD
