Metadata-Version: 2.1
Name: PyoSolveWrapper
Version: 0.3.2
Summary: Wrapper for Pyomo solve method
Home-page: https://github.com/judejeh/PyomoSolverWrapper
Download-URL: https://github.com/judejeh/PyomoSolverWrapper/archive/refs/tags/v0.3.1.tar.gz
Author: Jude Ejeh, Solomon F. Brown
Author-email: joe@judejeh.com
License: MIT
Platform: UNKNOWN
Classifier: Development Status :: 4 - Beta
Classifier: Intended Audience :: End Users/Desktop
Classifier: Intended Audience :: Science/Research
Classifier: License :: OSI Approved :: MIT License
Classifier: Natural Language :: English
Classifier: Operating System :: MacOS
Classifier: Operating System :: Microsoft :: Windows
Classifier: Operating System :: Unix
Classifier: Programming Language :: Python
Classifier: Programming Language :: Python :: 3
Classifier: Programming Language :: Python :: 3.5
Classifier: Programming Language :: Python :: 3.6
Classifier: Programming Language :: Python :: 3.7
Classifier: Programming Language :: Python :: 3.8
Classifier: Programming Language :: Python :: 3.9
Classifier: Programming Language :: Python :: Implementation :: CPython
Classifier: Topic :: Scientific/Engineering :: Mathematics
Classifier: Topic :: Software Development :: Libraries :: Python Modules
Requires-Python: >=3.5
License-File: LICENSE
Requires-Dist: pyomo (<=6.0.1)
Requires-Dist: numpy
Requires-Dist: pyutilib (>=5.7.3)
